varlink/__init__.py
varlink/cli.py
varlink/client.py
varlink/error.py
varlink/mock.py
varlink/org.varlink.service.varlink
varlink/scanner.py
varlink/server.py
varlink/tests/__init__.py
varlink/tests/org.example.more.varlink
varlink/tests/org.varlink.certification.varlink
varlink/tests/test_basic_network.py
varlink/tests/test_certification.py
varlink/tests/test_mocks.py
varlink/tests/test_orgexamplemore.py
varlink/tests/test_scanner.py
varlink-31.0.0.dist-info/LICENSE.txt
varlink-31.0.0.dist-info/METADATA
varlink-31.0.0.dist-info/WHEEL
varlink-31.0.0.dist-info/top_level.txt
varlink-31.0.0.dist-info/RECORD
