Metadata-Version: 2.1
Name: varlink
Version: 31.0.0
Summary: Python implementation of the Varlink protocol
Home-page: https://github.com/varlink/python
Author: Lars Karlitski<lars@karlitski.net>, Harald Hoyer<harald@hoyer.xyz>
Author-email: harald@hoyer.xyz
License: ASL 2.0
Keywords: ipc,varlink,rpc
Platform: UNKNOWN
Classifier: Development Status :: 5 - Production/Stable
Classifier: Intended Audience :: Developers
Classifier: License :: OSI Approved :: Apache Software License
Classifier: Programming Language :: Python
Classifier: Programming Language :: Python :: 2.7
Classifier: Programming Language :: Python :: 3
Classifier: Programming Language :: Python :: 3.5
Classifier: Programming Language :: Python :: 3.6
Classifier: Programming Language :: Python :: 3.7
Classifier: Programming Language :: Python :: 3.8
Classifier: Topic :: System :: Networking
Requires-Python: !=3.0.*,!=3.1.*,!=3.2.*,!=3.3.*,!=3.4.*,>=2.7
License-File: LICENSE.txt
